{
  "name": "炼气期功法术法",
  "category": "seeking_immortals:basics",
  "icon": "seeking_immortals:spirit_charm",
  "sortnum": 6,
  "pages": [
    {
      "type": "patchouli:text",
      "title": "规则定位",
      "text": "炼气期可掌握入门修炼功法、五行基础术法、低阶符箓、身法遁术与少量世俗武技。这些内容当前作为规则数据记录，供后续功法学习、宗门传承、任务奖励与灵根属性加成系统接入。"
    },
    {
      "type": "patchouli:text",
      "title": "通用与辅助",
      "text": "引气术：修炼一切功法术法的前提。$(br)传音术：数里内私密联络。$(br)控物术：隔空取物与操控器物。$(br)天眼术：观察灵力波动、看破简单幻象。$(br)匿身术、隐形术：潜行与逃脱。"
    },
    {
      "type": "patchouli:text",
      "title": "五行攻击控场",
      "text": "火花术、火弹术为火系入门攻击；冰冻术为水/冰系低耗攻击；缠绕术为木系限制；地刺术、流沙术为土系攻击与困敌。定神符可短暂定住神魂，对低阶妖兽更有效。"
    },
    {
      "type": "patchouli:text",
      "title": "身法与武技",
      "text": "升空术可短暂腾空，御风诀更快且更灵活。龟息功适合假死潜伏，罗烟步注重短距爆发，眨眼剑法利用视觉误差扰敌，象甲功强化肉身防御，雪风剑法以冰寒剑气迟缓敌人。"
    }
  ]
}
